tdexchange/__init__.py
tdexchange/bot.py
tdexchange/client.py
tdexchange/runner.py
tdexchange-0.0.2.dist-info/METADATA
tdexchange-0.0.2.dist-info/WHEEL
tdexchange-0.0.2.dist-info/licenses/LICENSE.txt
tdexchange-0.0.2.dist-info/RECORD
