Metadata-Version: 2.1
Name: tdexchange
Version: 0.0.2
Summary: Python Client for the TdExchange Server
Author-email: Terry Qi <troppydash.developer@gmail.com>
License: Mozilla Public License Version 2.0
License-File: LICENSE.txt
Requires-Python: >=3.8
Requires-Dist: websocket-client
